tuya_strip/__init__.py
tuya_strip/__main__.py
tuya_strip/cli.py
tuya_strip-0.1.2.dist-info/METADATA
tuya_strip-0.1.2.dist-info/WHEEL
tuya_strip-0.1.2.dist-info/entry_points.txt
tuya_strip-0.1.2.dist-info/licenses/LICENSE
tuya_strip-0.1.2.dist-info/RECORD
