Metadata-Version: 2.4
Name: tuya-strip
Version: 0.1.2
Summary: CLI for controlling a Tuya 3-way power strip over LAN
License-File: LICENSE
Author: wanjawischmeier
Requires-Python: >=3.13
Classifier: Programming Language :: Python :: 3
Classifier: Programming Language :: Python :: 3.13
Classifier: Programming Language :: Python :: 3.14
Requires-Dist: python-dotenv (>=1.1.1,<2.0.0)
Requires-Dist: tinytuya (>=1.17.4,<2.0.0)
